README.rst
setup.py
tests/__init__.py
tests/test.py
tomorrow/__init__.py
tomorrow/tomorrow.py
tomorrow.egg-info/PKG-INFO
tomorrow.egg-info/SOURCES.txt
tomorrow.egg-info/dependency_links.txt
tomorrow.egg-info/requires.txt
tomorrow.egg-info/top_level.txt