Metadata-Version: 1.0
Name: tomorrow
Version: 0.2.3
Summary: 
Home-page: https://github.com/madisonmay/tomorrow
Author: Madison May
Author-email: madison@indico.io
License: MIT License (See LICENSE)
Platform: UNKNOWN
